allure_additions/__init__.py
allure_additions/allure_prefix.py
allure_additions/conftest.py
allure_additions-1.0.12.dist-info/METADATA
allure_additions-1.0.12.dist-info/WHEEL
allure_additions-1.0.12.dist-info/entry_points.txt
allure_additions-1.0.12.dist-info/top_level.txt
allure_additions-1.0.12.dist-info/RECORD
