Metadata-Version: 2.1
Name: allure-additions
Version: 1.0.12
Summary: pytest plugin for adding additional information into allure report
Home-page: UNKNOWN
Author: Nikita Kuznetsov
Author-email: UNKNOWN
License: UNKNOWN
Platform: UNKNOWN
Requires-Dist: pytest (>=2)
Requires-Dist: pytest-allure-adaptor (>=1.7.10)
Requires-Dist: future
